Metadata-Version: 2.1
Name: odoo14-addon-l10n_br_account_payment_brcobranca
Version: 14.0.7.2.2
Summary: receivable Boletos and CNAB using the BRCobranca lib
Home-page: https://github.com/OCA/l10n-brazil
Author: Akretion, Odoo Community Association (OCA)
Author-email: support@odoo-community.org
License: AGPL-3
Classifier: Programming Language :: Python
Classifier: Framework :: Odoo
Classifier: Framework :: Odoo :: 14.0
Classifier: License :: OSI Approved :: GNU Affero General Public License v3
Requires-Python: >=3.6
Requires-Dist: erpbrasil.base
Requires-Dist: odoo14-addon-account-move-base-import
Requires-Dist: odoo14-addon-l10n-br-account-payment-order
Requires-Dist: odoo<14.1dev,>=14.0a
